__modern_types__/__init__.py
__modern_types__/_registrars.py
__modern_types__/_registry.py
__modern_types__/py.typed
modern_types-2.0.8.dist-info/LICENSE
modern_types-2.0.8.dist-info/METADATA
modern_types-2.0.8.dist-info/WHEEL
modern_types-2.0.8.dist-info/RECORD
