Metadata-Version: 2.1
Name: modern_types
Version: 2.0.8
Summary: PEP 585 + PEP 604 backports.
Home-page: https://github.com/bswck/modern_types
License: MIT
Author: bswck
Author-email: bswck.dev@gmail.com
Requires-Python: >=3.8,<=3.12
Classifier: License :: OSI Approved :: MIT License
Classifier: Programming Language :: Python :: 3
Classifier: Programming Language :: Python :: 3.8
Classifier: Programming Language :: Python :: 3.9
Classifier: Programming Language :: Python :: 3.10
Classifier: Programming Language :: Python :: 3.11
Classifier: Programming Language :: Python :: 3.12
Project-URL: Coverage, https://coverage-badge.samuelcolvin.workers.dev/redirect/bswck/modern_types
Project-URL: Distribution, https://pypi.org/project/modern-types/
Project-URL: Issues, https://github.com/bswck/modern_types/issues
